Metadata-Version: 2.1
Name: forward-decl
Version: 0.1.2
Summary: A simple module for supporting forward references
Author: LMauricius
License-File: LICENSE
